build_vc/__init__.py
build_vc/cffi_helpers.py
pystm32flash/__init__.py
pystm32flash/cffi_helpers.py
pystm32flash_src/__init__.py
pystm32flash_src/cffi_helpers.py
pystm32flash_src/tools.py
pystm32flash-0.0.4.dist-info/LICENSE
pystm32flash-0.0.4.dist-info/METADATA
pystm32flash-0.0.4.dist-info/WHEEL
pystm32flash-0.0.4.dist-info/entry_points.txt
pystm32flash-0.0.4.dist-info/top_level.txt
pystm32flash-0.0.4.dist-info/RECORD
